wavplot/__init__.py
wavplot-0.1.1.dist-info/METADATA
wavplot-0.1.1.dist-info/WHEEL
wavplot-0.1.1.dist-info/entry_points.txt
wavplot-0.1.1.dist-info/top_level.txt
wavplot-0.1.1.dist-info/RECORD
