Metadata-Version: 2.1
Name: wavplot
Version: 0.1.1
Summary: Generate waveform and spectrogram png images from a wav file
Home-page: https://github.com/nils-werner/wavplot
Author: Fabian-Robert Stöter, Nils Werner
Author-email: mail@faroit.com, nils@hey.com
License: MIT
Keywords: audio
Platform: any
Classifier: Intended Audience :: Developers
Classifier: Intended Audience :: Science/Research
Classifier: License :: OSI Approved :: MIT License
Classifier: Natural Language :: English
Classifier: Operating System :: OS Independent
Classifier: Programming Language :: Python
Classifier: Topic :: Multimedia :: Sound/Audio
Requires-Dist: scipy
Requires-Dist: numpy
Requires-Dist: matplotlib
Requires-Dist: PySoundFile (>=0.7.0)
